pybase3/__init__.py
pybase3/__main__.py
pybase3/dbase3.py
pybase3/dbfquery.py
pybase3/dbfview.py
pybase3/header_reader.py
pybase3/hexreader.py
pybase3/sqlparser.py
pybase3/test.py
pybase3/utils.py
pybase3-2.1.5.dist-info/LICENSE
pybase3-2.1.5.dist-info/METADATA
pybase3-2.1.5.dist-info/WHEEL
pybase3-2.1.5.dist-info/entry_points.txt
pybase3-2.1.5.dist-info/top_level.txt
pybase3-2.1.5.dist-info/RECORD
