Metadata-Version: 2.1
Name: pybase3
Version: 2.1.5
Summary: A Python library to manipulate DBase III database files
Home-page: https://github.com/sandy98/pybase3
Author: Domingo E. Savoretti
Author-email: esavoretti@gmail.com
License: MIT
Platform: UNKNOWN
Classifier: Programming Language :: Python :: 3
Classifier: License :: OSI Approved :: MIT License
Classifier: Operating System :: OS Independent
Requires-Python: >=3.6
License-File: LICENSE
